robothub_oak/__init__.py
robothub_oak/application.py
robothub_oak/events.py
robothub_oak/live_view.py
robothub_oak/types.py
robothub_oak/utils.py
robothub_oak-2.1.0.dist-info/LICENSE
robothub_oak-2.1.0.dist-info/METADATA
robothub_oak-2.1.0.dist-info/WHEEL
robothub_oak-2.1.0.dist-info/top_level.txt
robothub_oak-2.1.0.dist-info/RECORD
