Metadata-Version: 2.1
Name: robothub-oak
Version: 2.1.0
Summary: RobotHub integration library
Home-page: https://www.luxonis.com/
Author: Luxonis
Author-email: support@luxonis.com
License: MIT
Project-URL: Homepage, https://github.com/luxonis/robothub/
Project-URL: Documentation, https://hub-docs.luxonis.com/
Keywords: robothub camera robot hub connect agent depthai sdk
Classifier: Development Status :: 4 - Beta
Classifier: Intended Audience :: Developers
Classifier: Intended Audience :: Education
Classifier: Intended Audience :: Information Technology
Classifier: Intended Audience :: Science/Research
Classifier: Programming Language :: Python
Classifier: Programming Language :: Python :: 3.10
Classifier: License :: OSI Approved :: MIT License
Classifier: Operating System :: Unix
Classifier: Topic :: Software Development
Classifier: Topic :: Scientific/Engineering
License-File: LICENSE
